mypass/__init__.py
mypass/browser.py
mypass/cli.py
mypass/client.py
mypass/config.py
mypass/daemon.py
mypass/db.py
mypass/migration.py
mypass/extension/background.js
mypass/extension/content.js
mypass/extension/icon-16.png
mypass/extension/icon-19.png
mypass/extension/icon-32.png
mypass/extension/icon-38.png
mypass/extension/manifest.json
mypass/extension/popup.html
mypass/extension/popup.js
mypass/native-messaging-hosts/chrome/org.snoack.mypass.json
mypass/native-messaging-hosts/mozilla/org.snoack.mypass.json
mypass-2.1.data/scripts/mypass
mypass-2.1.dist-info/METADATA
mypass-2.1.dist-info/WHEEL
mypass-2.1.dist-info/top_level.txt
mypass-2.1.dist-info/RECORD
