Metadata-Version: 2.4
Name: mypass
Version: 2.1
Summary: A secure password manager with command line interface
Home-page: https://github.com/snoack/mypass
Author: Sebastian Noack
Author-email: sebstian.noack@gmail.com
Classifier: Development Status :: 5 - Production/Stable
Classifier: Intended Audience :: End Users/Desktop
Classifier: Intended Audience :: Information Technology
Classifier: License :: OSI Approved :: GNU General Public License v3 or later (GPLv3+)
Classifier: Operating System :: POSIX
Classifier: Programming Language :: Python
Classifier: Programming Language :: Python :: 3
Classifier: Topic :: Security
Classifier: Topic :: Utilities
Requires-Python: >=3.4
Requires-Dist: pycrypto
Requires-Dist: argcomplete
Dynamic: author
Dynamic: author-email
Dynamic: classifier
Dynamic: description
Dynamic: description-content-type
Dynamic: home-page
Dynamic: requires-dist
Dynamic: requires-python
Dynamic: summary
